{
  "hash": "47291e02",
  "configHash": "827014d1",
  "lockfileHash": "650a6f9d",
  "browserHash": "ba6ee35e",
  "optimized": {
    "vue": {
      "src": "../../../../node_modules/vue/dist/vue.runtime.esm-bundler.js",
      "file": "vue.js",
      "fileHash": "79bd81e9",
      "needsInterop": false
    },
    "vitepress > @vue/devtools-api": {
      "src": "../../../../node_modules/@vue/devtools-api/dist/index.js",
      "file": "vitepress___@vue_devtools-api.js",
      "fileHash": "2b1af383",
      "needsInterop": false
    },
    "vitepress > @vueuse/core": {
      "src": "../../../../node_modules/@vueuse/core/index.mjs",
      "file": "vitepress___@vueuse_core.js",
      "fileHash": "395ed2db",
      "needsInterop": false
    },
    "vitepress > @vueuse/integrations/useFocusTrap": {
      "src": "../../../../node_modules/@vueuse/integrations/useFocusTrap.mjs",
      "file": "vitepress___@vueuse_integrations_useFocusTrap.js",
      "fileHash": "b8cc55e5",
      "needsInterop": false
    },
    "vitepress > mark.js/src/vanilla.js": {
      "src": "../../../../node_modules/mark.js/src/vanilla.js",
      "file": "vitepress___mark__js_src_vanilla__js.js",
      "fileHash": "64a726e4",
      "needsInterop": false
    },
    "vitepress > minisearch": {
      "src": "../../../../node_modules/minisearch/dist/es/index.js",
      "file": "vitepress___minisearch.js",
      "fileHash": "e944906b",
      "needsInterop": false
    },
    "vitepress-plugin-image-viewer": {
      "src": "../../../../node_modules/vitepress-plugin-image-viewer/lib/viewer.js",
      "file": "vitepress-plugin-image-viewer.js",
      "fileHash": "5bf6177e",
      "needsInterop": false
    },
    "vitepress-plugin-comment-with-giscus": {
      "src": "../../../../node_modules/vitepress-plugin-comment-with-giscus/lib/giscus.js",
      "file": "vitepress-plugin-comment-with-giscus.js",
      "fileHash": "5802c742",
      "needsInterop": false
    }
  },
  "chunks": {
    "giscus-aTimukGI-27DZ4DKL": {
      "file": "giscus-aTimukGI-27DZ4DKL.js"
    },
    "chunk-IGGLDVEO": {
      "file": "chunk-IGGLDVEO.js"
    },
    "chunk-UPQBEO3K": {
      "file": "chunk-UPQBEO3K.js"
    }
  }
}